bliss_bind-0.3.0.dist-info/RECORD
bliss_bind-0.3.0.dist-info/WHEEL
bliss_bind-0.3.0.dist-info/METADATA
bliss_bind-0.3.0.dist-info/licenses/LICENSE
bliss_bind/__init__.py
bliss_bind/bliss_bind_ext.cpython-39-darwin.so
